jotui/__init__.py
jotui-0.0.1.dist-info/METADATA
jotui-0.0.1.dist-info/WHEEL
jotui-0.0.1.dist-info/licenses/LICENSE
jotui-0.0.1.dist-info/RECORD
